bompy
