Metadata-Version: 1.0
Name: bompy
Version: 0.1.2
Summary: A very light wrapper around the www.bom.gov.au weather data api.
Home-page: https://github.com/adamjoshuagray/bompy
Author: Adam J. Gray
Author-email: adam.joshua.gray@gmail.com
License: MIT
Platform: UNKNOWN
